README.rst
consul_options.py
setup.py
consul_options.egg-info/PKG-INFO
consul_options.egg-info/SOURCES.txt
consul_options.egg-info/dependency_links.txt
consul_options.egg-info/requires.txt
consul_options.egg-info/top_level.txt